{"ts": 1756301889.7008455, "payload": {"bathrooms": 4, "carouselPhotos": null, "has3DModel": true, "propertyType": "SINGLE_FAMILY", "longitude": -82.50407, "livingArea": 4227, "address": "911 S Sterling Ave, Tampa, FL 33629", "rentZestimate": null, "variableData": null, "priceChange": null, "zestimate": null, "imgSrc": "https://photos.zillowstatic.com/fp/ff77c626d1a9910de9684c7208dbb4a2-p_e.jpg", "latitude": 27.931637, "price": 2490000, "bedrooms": 5, "lotAreaValue": 0.25826446280992, "hasVideo": false, "lotAreaUnit": "acres", "listingStatus": "FOR_SALE", "zpid": "166721500", "listingSubType": {"is_FSBA": true}, "detailUrl": "/homedetails/911-S-Sterling-Ave-Tampa-FL-33629/166721500_zpid/", "contingentListingType": null, "daysOnZillow": 5, "datePriceChanged": null, "country": "USA", "currency": "USD", "comingSoonOnMarketDate": null, "hasImage": true}}