{"ts": 1756232454.015298, "payload": {"bathrooms": 2, "carouselPhotos": null, "has3DModel": false, "propertyType": "SINGLE_FAMILY", "longitude": -80.23261, "livingArea": 1331, "address": "2305 SW 19th Ter, Miami, FL 33145", "rentZestimate": 4275, "variableData": null, "priceChange": -54000, "zestimate": 870100, "imgSrc": "https://photos.zillowstatic.com/fp/3007649cfb82b61fea55d5bde0a5f1f0-p_e.jpg", "latitude": 25.753744, "price": 915000, "bedrooms": 2, "lotAreaValue": 5500, "hasVideo": false, "lotAreaUnit": "sqft", "listingStatus": "FOR_SALE", "zpid": "43852003", "listingSubType": {"is_FSBA": true}, "detailUrl": "/homedetails/2305-SW-19th-Ter-Miami-FL-33145/43852003_zpid/", "contingentListingType": null, "daysOnZillow": 73, "datePriceChanged": 1755241200000, "country": "USA", "currency": "USD", "comingSoonOnMarketDate": null, "hasImage": true}}