{"ts": 1756248614.62022, "payload": {"bathrooms": 2, "carouselPhotos": null, "has3DModel": true, "propertyType": "SINGLE_FAMILY", "longitude": -80.20831, "livingArea": 1688, "address": "920 SW 8th Ct, Miami, FL 33130", "rentZestimate": null, "variableData": null, "priceChange": 99, "zestimate": null, "imgSrc": "https://photos.zillowstatic.com/fp/72152b29bab44a7d51ccc7a7943949e1-p_e.jpg", "latitude": 25.764603, "price": 699999, "bedrooms": 6, "lotAreaValue": 4850, "hasVideo": false, "lotAreaUnit": "sqft", "listingStatus": "FOR_SALE", "zpid": "43865821", "listingSubType": {"is_FSBA": true}, "detailUrl": "/homedetails/920-SW-8th-Ct-Miami-FL-33130/43865821_zpid/", "contingentListingType": null, "daysOnZillow": 22, "datePriceChanged": 1754290800000, "country": "USA", "currency": "USD", "comingSoonOnMarketDate": null, "hasImage": true}}