{"ts": 1756248655.3590496, "payload": {"bathrooms": 3, "carouselPhotos": null, "has3DModel": false, "propertyType": "SINGLE_FAMILY", "longitude": -80.23038, "livingArea": 932, "address": "1934 NW 84th St, Miami, FL 33147", "rentZestimate": 2993, "variableData": null, "priceChange": null, "zestimate": 485400, "imgSrc": "https://photos.zillowstatic.com/fp/a845dd102ce27f31e1355efa96a3dc55-p_e.jpg", "latitude": 25.851128, "price": 490500, "bedrooms": 3, "lotAreaValue": 5057, "hasVideo": false, "lotAreaUnit": "sqft", "listingStatus": "FOR_SALE", "zpid": "44155593", "listingSubType": {"is_FSBA": true}, "detailUrl": "/homedetails/1934-NW-84th-St-Miami-FL-33147/44155593_zpid/", "contingentListingType": null, "daysOnZillow": 134, "datePriceChanged": null, "country": "USA", "currency": "USD", "comingSoonOnMarketDate": null, "hasImage": true}}