{"ts": 1756248642.8711643, "payload": {"bathrooms": 3, "carouselPhotos": null, "has3DModel": false, "propertyType": "SINGLE_FAMILY", "longitude": -80.32425, "livingArea": 2890, "address": "7895 Grand Canal Dr, Miami, FL 33144", "rentZestimate": null, "variableData": null, "priceChange": null, "zestimate": null, "imgSrc": "https://photos.zillowstatic.com/fp/ebd7d09452dcbe50ec01f9f0af180421-p_e.jpg", "latitude": 25.76346, "price": 1295000, "bedrooms": 5, "lotAreaValue": 0.57300275482094, "hasVideo": false, "lotAreaUnit": "acres", "listingStatus": "FOR_SALE", "zpid": "44167984", "listingSubType": {"is_FSBA": true}, "detailUrl": "/homedetails/7895-Grand-Canal-Dr-Miami-FL-33144/44167984_zpid/", "contingentListingType": null, "daysOnZillow": 18, "datePriceChanged": null, "country": "USA", "currency": "USD", "comingSoonOnMarketDate": null, "hasImage": true}}