{"ts": 1756241640.8798082, "payload": {"bathrooms": 3, "carouselPhotos": null, "has3DModel": false, "propertyType": "SINGLE_FAMILY", "longitude": -82.60458, "livingArea": 2490, "address": "11230 Bloomington Dr, Tampa, FL 33635", "rentZestimate": null, "variableData": null, "priceChange": null, "zestimate": null, "imgSrc": "https://photos.zillowstatic.com/fp/17a314f9fd2da79cfca1c2f15a8c4c2f-p_e.jpg", "latitude": 28.035454, "price": 669900, "bedrooms": 4, "lotAreaValue": 9650, "hasVideo": false, "lotAreaUnit": "sqft", "listingStatus": "FOR_SALE", "zpid": "44860067", "listingSubType": {"is_FSBA": true}, "detailUrl": "/homedetails/11230-Bloomington-Dr-Tampa-FL-33635/44860067_zpid/", "contingentListingType": null, "daysOnZillow": 2, "datePriceChanged": null, "country": "USA", "currency": "USD", "comingSoonOnMarketDate": null, "hasImage": true}}