{"ts": 1756241611.733593, "payload": {"bathrooms": 3, "carouselPhotos": null, "has3DModel": false, "propertyType": "SINGLE_FAMILY", "longitude": -82.5541, "livingArea": 1100, "address": "6706 W Clifton St, Tampa, FL 33634", "rentZestimate": 2448, "variableData": null, "priceChange": -9000, "zestimate": 419100, "imgSrc": "https://photos.zillowstatic.com/fp/543e5f88bb4a9f9aebd1afdfedc5d3cd-p_e.jpg", "latitude": 28.000383, "price": 420000, "bedrooms": 3, "lotAreaValue": 6343, "hasVideo": false, "lotAreaUnit": "sqft", "listingStatus": "FOR_SALE", "zpid": "44873227", "listingSubType": {"is_FSBA": true}, "detailUrl": "/homedetails/6706-W-Clifton-St-Tampa-FL-33634/44873227_zpid/", "contingentListingType": null, "daysOnZillow": 47, "datePriceChanged": 1754463600000, "country": "USA", "currency": "USD", "comingSoonOnMarketDate": null, "hasImage": true}}