{"ts": 1756247126.7161226, "payload": {"bathrooms": 2, "carouselPhotos": null, "has3DModel": false, "newConstructionType": "BUILDER_SPEC", "propertyType": "SINGLE_FAMILY", "longitude": -82.508194, "livingArea": 1656, "address": "3917 W Robson St, Tampa, FL 33614", "rentZestimate": 2530, "variableData": null, "priceChange": null, "zestimate": null, "imgSrc": "https://photos.zillowstatic.com/fp/0ba05c172a3c6767daa9eb3de0eb1f76-p_e.jpg", "latitude": 28.017235, "price": 540000, "bedrooms": 4, "lotAreaValue": 5227, "hasVideo": false, "lotAreaUnit": "sqft", "listingStatus": "FOR_SALE", "zpid": "44915526", "listingSubType": {"is_newHome": true}, "detailUrl": "/homedetails/3917-W-Robson-St-Tampa-FL-33614/44915526_zpid/", "contingentListingType": null, "daysOnZillow": 133, "datePriceChanged": null, "country": "USA", "currency": "USD", "comingSoonOnMarketDate": null, "hasImage": true}}