{"ts": 1756264888.1471105, "payload": {"bathrooms": 4, "carouselPhotos": null, "has3DModel": true, "propertyType": "SINGLE_FAMILY", "longitude": -82.495895, "livingArea": 3310, "address": "4515 N Saint Vincent St, Tampa, FL 33614", "rentZestimate": 3978, "variableData": null, "priceChange": null, "zestimate": null, "imgSrc": "https://maps.googleapis.com/maps/api/staticmap?mobile=false&sensor=true&maptype=satellite&size=575x242&zoom=17&center=27.986370086669922,-82.49589538574219&key=AIzaSyBWYJWCA8FNMQvSe_k3LKfDGJaEgdKwsco&signature=bJJ5cWJas02f6OacIiprdyiKJfg=", "latitude": 27.98637, "price": 555000, "bedrooms": 5, "lotAreaValue": 6969, "hasVideo": false, "lotAreaUnit": "sqft", "listingStatus": "FOR_SALE", "zpid": "45042728", "listingSubType": {"is_FSBO": true}, "detailUrl": "/homedetails/4515-N-Saint-Vincent-St-Tampa-FL-33614/45042728_zpid/", "contingentListingType": null, "daysOnZillow": 6, "datePriceChanged": null, "country": "USA", "currency": "USD", "comingSoonOnMarketDate": null, "hasImage": null}}