{"ts": 1756247777.8924713, "payload": {"bathrooms": 3, "carouselPhotos": null, "has3DModel": false, "propertyType": "SINGLE_FAMILY", "longitude": -82.49706, "livingArea": 3384, "address": "3302 W Caracas St, Tampa, FL 33614", "rentZestimate": 5384, "variableData": null, "priceChange": -10000, "zestimate": 848600, "imgSrc": "https://photos.zillowstatic.com/fp/c7abc9026aa071b99ff5b272fa089300-p_e.jpg", "latitude": 27.991737, "price": 878000, "bedrooms": 4, "lotAreaValue": 0.27456382001837, "hasVideo": false, "lotAreaUnit": "acres", "listingStatus": "FOR_SALE", "zpid": "45042530", "listingSubType": {"is_FSBA": true}, "detailUrl": "/homedetails/3302-W-Caracas-St-Tampa-FL-33614/45042530_zpid/", "contingentListingType": null, "daysOnZillow": 133, "datePriceChanged": 1755759600000, "country": "USA", "currency": "USD", "comingSoonOnMarketDate": null, "hasImage": true}}