{"ts": 1756241650.0830984, "payload": {"bathrooms": 2, "carouselPhotos": null, "has3DModel": false, "propertyType": "SINGLE_FAMILY", "longitude": -82.50783, "livingArea": 1301, "address": "6321 S Harold Ave, Tampa, FL 33616", "rentZestimate": 2286, "variableData": null, "priceChange": -6000, "zestimate": 451000, "imgSrc": "https://photos.zillowstatic.com/fp/9ede59c0812359b6e0e218983256bb37-p_e.jpg", "latitude": 27.874043, "price": 459000, "bedrooms": 3, "lotAreaValue": 5350, "hasVideo": false, "lotAreaUnit": "sqft", "listingStatus": "FOR_SALE", "zpid": "45071238", "listingSubType": {"is_FSBA": true}, "detailUrl": "/homedetails/6321-S-Harold-Ave-Tampa-FL-33616/45071238_zpid/", "contingentListingType": null, "daysOnZillow": 20, "datePriceChanged": 1755846000000, "country": "USA", "currency": "USD", "comingSoonOnMarketDate": null, "hasImage": true}}