{"ts": 1756241539.2273953, "payload": {"bathrooms": 2, "carouselPhotos": null, "has3DModel": false, "propertyType": "SINGLE_FAMILY", "longitude": -82.42557, "livingArea": 1805, "address": "3011 E Ellicott St, Tampa, FL 33610", "rentZestimate": 2113, "variableData": null, "priceChange": null, "zestimate": null, "imgSrc": "https://photos.zillowstatic.com/fp/640c37faff363322ad3e87f260b12d4c-p_e.jpg", "latitude": 27.990326, "price": 195000, "bedrooms": 3, "lotAreaValue": 6987, "hasVideo": false, "lotAreaUnit": "sqft", "listingStatus": "FOR_SALE", "zpid": "45087085", "listingSubType": {"is_bankOwned": true}, "detailUrl": "/homedetails/3011-E-Ellicott-St-Tampa-FL-33610/45087085_zpid/", "contingentListingType": "FORECLOSURE", "daysOnZillow": 28, "datePriceChanged": null, "country": "USA", "currency": "USD", "comingSoonOnMarketDate": null, "hasImage": true}}