{"ts": 1756301078.2251694, "payload": {"bathrooms": 1, "carouselPhotos": null, "has3DModel": true, "propertyType": "SINGLE_FAMILY", "longitude": -82.45004, "livingArea": 1441, "address": "5803 Roberta Cir, Tampa, FL 33604", "rentZestimate": null, "variableData": null, "priceChange": null, "zestimate": null, "imgSrc": "https://photos.zillowstatic.com/fp/47511207ce244eaac52910d690e24059-p_e.jpg", "latitude": 28.000097, "price": 548000, "bedrooms": 3, "lotAreaValue": 10764, "hasVideo": false, "lotAreaUnit": "sqft", "listingStatus": "FOR_SALE", "zpid": "45097312", "listingSubType": {"is_FSBA": true, "is_openHouse": true}, "detailUrl": "/homedetails/5803-Roberta-Cir-Tampa-FL-33604/45097312_zpid/", "contingentListingType": null, "daysOnZillow": 11, "datePriceChanged": null, "country": "USA", "currency": "USD", "comingSoonOnMarketDate": null, "hasImage": true}}