{"ts": 1756246483.1287913, "payload": {"bathrooms": 2, "carouselPhotos": null, "has3DModel": false, "propertyType": "SINGLE_FAMILY", "longitude": -82.456276, "livingArea": 998, "address": "502 E Cluster Ave, Tampa, FL 33604", "rentZestimate": 2228, "variableData": null, "priceChange": null, "zestimate": 311900, "imgSrc": "https://photos.zillowstatic.com/fp/88a53c5349171e78af9c61a451c89715-p_e.jpg", "latitude": 28.01358, "price": 289000, "bedrooms": 3, "lotAreaValue": 4697, "hasVideo": false, "lotAreaUnit": "sqft", "listingStatus": "FOR_SALE", "zpid": "45090495", "listingSubType": {"is_bankOwned": true}, "detailUrl": "/homedetails/502-E-Cluster-Ave-Tampa-FL-33604/45090495_zpid/", "contingentListingType": "FORECLOSURE", "daysOnZillow": 0, "datePriceChanged": null, "country": "USA", "currency": "USD", "comingSoonOnMarketDate": null, "hasImage": true}}