{"ts": 1756265861.2706563, "payload": {"bathrooms": 5, "carouselPhotos": null, "has3DModel": false, "propertyType": "SINGLE_FAMILY", "longitude": -82.46016, "livingArea": 5157, "address": "441 Lucerne Ave, Tampa, FL 33606", "rentZestimate": 7621, "variableData": null, "priceChange": -150000, "zestimate": null, "imgSrc": "https://photos.zillowstatic.com/fp/96889aeba017341b94757a19d9e87338-p_e.jpg", "latitude": 27.919025, "price": 2000000, "bedrooms": 4, "lotAreaValue": 9271, "hasVideo": false, "lotAreaUnit": "sqft", "listingStatus": "FOR_SALE", "zpid": "45111331", "listingSubType": {"is_FSBA": true}, "detailUrl": "/homedetails/441-Lucerne-Ave-Tampa-FL-33606/45111331_zpid/", "contingentListingType": null, "daysOnZillow": 140, "datePriceChanged": 1751094000000, "country": "USA", "currency": "USD", "comingSoonOnMarketDate": null, "hasImage": true}}