{"ts": 1756301889.7856185, "payload": {"bathrooms": 3, "carouselPhotos": null, "has3DModel": false, "propertyType": "SINGLE_FAMILY", "longitude": -82.51126, "livingArea": 1791, "address": "4011 W El Prado Blvd, Tampa, FL 33629", "rentZestimate": null, "variableData": null, "priceChange": null, "zestimate": null, "imgSrc": "https://photos.zillowstatic.com/fp/dbe8f4cf4de2d6221eb74367bcee803d-p_e.jpg", "latitude": 27.911825, "price": 750000, "bedrooms": 4, "lotAreaValue": 9000, "hasVideo": false, "lotAreaUnit": "sqft", "listingStatus": "FOR_SALE", "zpid": "455871315", "listingSubType": {"is_FSBA": true}, "detailUrl": "/homedetails/4011-W-El-Prado-Blvd-Tampa-FL-33629/455871315_zpid/", "contingentListingType": null, "daysOnZillow": 15, "datePriceChanged": null, "country": "USA", "currency": "USD", "comingSoonOnMarketDate": null, "hasImage": true}}