{"ts": 1756301203.632134, "payload": {"bathrooms": 2, "carouselPhotos": null, "has3DModel": false, "propertyType": "SINGLE_FAMILY", "longitude": -82.697586, "livingArea": 1512, "address": "4753 48th Ave N, Saint Petersburg, FL 33714", "rentZestimate": null, "variableData": null, "priceChange": null, "zestimate": null, "imgSrc": "https://photos.zillowstatic.com/fp/68cb52cc84020d8281ed017c6e7165ce-p_e.jpg", "latitude": 27.815886, "price": 499000, "bedrooms": 3, "lotAreaValue": 7405, "hasVideo": false, "lotAreaUnit": "sqft", "listingStatus": "FOR_SALE", "zpid": "46976078", "listingSubType": {"is_FSBA": true}, "detailUrl": "/homedetails/4753-48th-Ave-N-Saint-Petersburg-FL-33714/46976078_zpid/", "contingentListingType": null, "daysOnZillow": 127, "datePriceChanged": null, "country": "USA", "currency": "USD", "comingSoonOnMarketDate": null, "hasImage": true}}