{"ts": 1756301151.0522032, "payload": {"bathrooms": 1, "carouselPhotos": null, "has3DModel": true, "propertyType": "SINGLE_FAMILY", "longitude": -82.70501, "livingArea": 924, "address": "5242 45th Ave N, Saint Petersburg, FL 33709", "rentZestimate": 2342, "variableData": null, "priceChange": null, "zestimate": 317700, "imgSrc": "https://photos.zillowstatic.com/fp/c5f0c4b5a17948473b557c899274b177-p_e.jpg", "latitude": 27.812729, "price": 330000, "bedrooms": 3, "lotAreaValue": 5672, "hasVideo": false, "lotAreaUnit": "sqft", "listingStatus": "FOR_SALE", "zpid": "46976391", "listingSubType": {"is_FSBA": true}, "detailUrl": "/homedetails/5242-45th-Ave-N-Saint-Petersburg-FL-33709/46976391_zpid/", "contingentListingType": null, "daysOnZillow": 1, "datePriceChanged": null, "country": "USA", "currency": "USD", "comingSoonOnMarketDate": null, "hasImage": true}}