{"ts": 1756299022.3668063, "payload": {"bathrooms": 2, "carouselPhotos": null, "has3DModel": false, "unit": "Apt 1802", "propertyType": "CONDO", "longitude": -82.64374, "livingArea": 1100, "address": "746 115th Ave N APT 1802, Saint Petersburg, FL 33716", "rentZestimate": null, "variableData": null, "priceChange": null, "zestimate": null, "imgSrc": "https://photos.zillowstatic.com/fp/11d7b5c5048b550cd35c2561bb6938bc-p_e.jpg", "latitude": 27.876907, "price": 220000, "bedrooms": 2, "lotAreaValue": 4.5018, "hasVideo": false, "lotAreaUnit": "acres", "listingStatus": "FOR_SALE", "zpid": "47109003", "listingSubType": {"is_FSBA": true}, "detailUrl": "/homedetails/746-115th-Ave-N-APT-1802-Saint-Petersburg-FL-33716/47109003_zpid/", "contingentListingType": null, "daysOnZillow": 20, "datePriceChanged": null, "country": "USA", "currency": "USD", "comingSoonOnMarketDate": null, "hasImage": true}}