{"ts": 1756301233.205401, "payload": {"bathrooms": 3, "carouselPhotos": null, "has3DModel": false, "propertyType": "SINGLE_FAMILY", "longitude": -82.7291, "livingArea": 2244, "address": "2490 E Vina Del Mar Blvd, Saint Pete Beach, FL 33706", "rentZestimate": 5751, "variableData": null, "priceChange": -74000, "zestimate": 670300, "imgSrc": "https://photos.zillowstatic.com/fp/6329578f4e49cb416073c888003122c0-p_e.jpg", "latitude": 27.699404, "price": 725000, "bedrooms": 3, "lotAreaValue": 7749, "hasVideo": false, "lotAreaUnit": "sqft", "listingStatus": "FOR_SALE", "zpid": "47113532", "listingSubType": {"is_FSBA": true}, "detailUrl": "/homedetails/2490-E-Vina-Del-Mar-Blvd-Saint-Pete-Beach-FL-33706/47113532_zpid/", "contingentListingType": null, "daysOnZillow": 154, "datePriceChanged": 1749020400000, "country": "USA", "currency": "USD", "comingSoonOnMarketDate": null, "hasImage": true}}