{"ts": 1756301151.0347629, "payload": {"bathrooms": 2, "carouselPhotos": null, "has3DModel": true, "propertyType": "SINGLE_FAMILY", "longitude": -82.74625, "livingArea": 1300, "address": "7869 Causeway Blvd S, Saint Petersburg, FL 33707", "rentZestimate": null, "variableData": null, "priceChange": null, "zestimate": null, "imgSrc": "https://photos.zillowstatic.com/fp/4a5b0c8db1e8a8a4ed0287242db65901-p_e.jpg", "latitude": 27.77054, "price": 789000, "bedrooms": 3, "lotAreaValue": 7501, "hasVideo": false, "lotAreaUnit": "sqft", "listingStatus": "FOR_SALE", "zpid": "47169310", "listingSubType": {"is_FSBA": true, "is_openHouse": true}, "detailUrl": "/homedetails/7869-Causeway-Blvd-S-Saint-Petersburg-FL-33707/47169310_zpid/", "contingentListingType": null, "daysOnZillow": 4, "datePriceChanged": null, "country": "USA", "currency": "USD", "comingSoonOnMarketDate": null, "hasImage": true}}