{"ts": 1756301170.8466492, "payload": {"bathrooms": 2, "carouselPhotos": null, "has3DModel": true, "propertyType": "SINGLE_FAMILY", "longitude": -82.64497, "livingArea": 1344, "address": "777 62nd Ave N, Saint Petersburg, FL 33702", "rentZestimate": 2396, "variableData": null, "priceChange": -19902, "zestimate": 370500, "imgSrc": "https://photos.zillowstatic.com/fp/462821220f50bd08bc5611b60c41e67c-p_e.jpg", "latitude": 27.828754, "price": 374998, "bedrooms": 3, "lotAreaValue": 5724, "hasVideo": false, "lotAreaUnit": "sqft", "listingStatus": "FOR_SALE", "zpid": "47243156", "listingSubType": {"is_FSBA": true, "is_openHouse": true}, "detailUrl": "/homedetails/777-62nd-Ave-N-Saint-Petersburg-FL-33702/47243156_zpid/", "contingentListingType": null, "daysOnZillow": 26, "datePriceChanged": 1754636400000, "country": "USA", "currency": "USD", "comingSoonOnMarketDate": null, "hasImage": true}}