{"ts": 1756241656.1000936, "payload": {"bathrooms": 4, "carouselPhotos": null, "has3DModel": true, "propertyType": "SINGLE_FAMILY", "longitude": -82.387924, "livingArea": 3124, "address": "17210 Broadoak Dr, Tampa, FL 33647", "rentZestimate": 4317, "variableData": null, "priceChange": null, "zestimate": 1283900, "imgSrc": "https://photos.zillowstatic.com/fp/c5e9e1019a744ffd40c77f2455bb9687-p_e.jpg", "latitude": 28.122734, "price": 1349900, "bedrooms": 4, "lotAreaValue": 0.25126262626263, "hasVideo": false, "lotAreaUnit": "acres", "listingStatus": "FOR_SALE", "zpid": "55331870", "listingSubType": {"is_FSBA": true}, "detailUrl": "/homedetails/17210-Broadoak-Dr-Tampa-FL-33647/55331870_zpid/", "contingentListingType": null, "daysOnZillow": 16, "datePriceChanged": null, "country": "USA", "currency": "USD", "comingSoonOnMarketDate": null, "hasImage": true}}