{"ts": 1756301191.8668563, "payload": {"bathrooms": 4, "carouselPhotos": null, "has3DModel": true, "propertyType": "SINGLE_FAMILY", "longitude": -82.605354, "livingArea": 3806, "address": "10643 Echo Lake Dr, Odessa, FL 33556", "rentZestimate": null, "variableData": null, "priceChange": null, "zestimate": null, "imgSrc": "https://photos.zillowstatic.com/fp/1a75526498b51e2fd80815a61363e6d9-p_e.jpg", "latitude": 28.110577, "price": 1290000, "bedrooms": 5, "lotAreaValue": 0.86136363636364, "hasVideo": false, "lotAreaUnit": "acres", "listingStatus": "FOR_SALE", "zpid": "66674065", "listingSubType": {"is_FSBA": true, "is_openHouse": true}, "detailUrl": "/homedetails/10643-Echo-Lake-Dr-Odessa-FL-33556/66674065_zpid/", "contingentListingType": null, "daysOnZillow": 10, "datePriceChanged": null, "country": "USA", "currency": "USD", "comingSoonOnMarketDate": null, "hasImage": true}}